langgraph_serve/__init__.py
langgraph_serve/_pydantic.py
langgraph_serve/api_handler.py
langgraph_serve/callbacks.py
langgraph_serve/chat_playground/.eslintrc.cjs
langgraph_serve/chat_playground/.gitignore
langgraph_serve/chat_playground/README.md
langgraph_serve/chat_playground/dist/assets/index-434ff580.css
langgraph_serve/chat_playground/dist/assets/index-53ad47d4.js
langgraph_serve/chat_playground/dist/favicon.ico
langgraph_serve/chat_playground/dist/index.html
langgraph_serve/chat_playground/index.html
langgraph_serve/chat_playground/package.json
langgraph_serve/chat_playground/postcss.config.js
langgraph_serve/chat_playground/public/favicon.ico
langgraph_serve/chat_playground/src/App.css
langgraph_serve/chat_playground/src/App.tsx
langgraph_serve/chat_playground/src/assets/ArrowUp.svg
langgraph_serve/chat_playground/src/assets/ChatIcon.svg
langgraph_serve/chat_playground/src/assets/CheckCircleIcon.svg
langgraph_serve/chat_playground/src/assets/CheckCircleIcon2.svg
langgraph_serve/chat_playground/src/assets/ChevronRight.svg
langgraph_serve/chat_playground/src/assets/CircleSpinIcon.svg
langgraph_serve/chat_playground/src/assets/CodeIcon.svg
langgraph_serve/chat_playground/src/assets/CopyIcon.svg
langgraph_serve/chat_playground/src/assets/EmptyState.svg
langgraph_serve/chat_playground/src/assets/LangServeLogo.svg
langgraph_serve/chat_playground/src/assets/PadlockIcon.svg
langgraph_serve/chat_playground/src/assets/PlusIcon.svg
langgraph_serve/chat_playground/src/assets/RefreshCW.svg
langgraph_serve/chat_playground/src/assets/SendIcon.svg
langgraph_serve/chat_playground/src/assets/ShareIcon.svg
langgraph_serve/chat_playground/src/assets/ThumbsDownIcon.svg
langgraph_serve/chat_playground/src/assets/ThumbsUpIcon.svg
langgraph_serve/chat_playground/src/assets/TrashIcon.svg
langgraph_serve/chat_playground/src/assets/XCircle.svg
langgraph_serve/chat_playground/src/components/AutosizeTextarea.tsx
langgraph_serve/chat_playground/src/components/ChatMessage.tsx
langgraph_serve-0.3.5.dist-info/LICENSE
langgraph_serve-0.3.5.dist-info/METADATA
langgraph_serve-0.3.5.dist-info/WHEEL
langgraph_serve-0.3.5.dist-info/RECORD
