Metadata-Version: 2.1
Name: langgraph_serve
Version: 0.3.5
Summary: 
Home-page: https://github.com/riyavsinha/langgraph-serve
License: LangServe
Author: Riya Sinha
Requires-Python: >=3.9,<4.0
Classifier: License :: Other/Proprietary License
Classifier: Programming Language :: Python :: 3
Classifier: Programming Language :: Python :: 3.9
Classifier: Programming Language :: Python :: 3.10
Classifier: Programming Language :: Python :: 3.11
Classifier: Programming Language :: Python :: 3.12
Provides-Extra: all
Provides-Extra: client
Provides-Extra: server
Requires-Dist: fastapi (>=0.90.1,<1) ; extra == "client" or extra == "server" or extra == "all"
Requires-Dist: httpx (>=0.23.0,<1.0)
Requires-Dist: langchain-core (>=0.3,<0.4)
Requires-Dist: langgraph (>=0.2.34,<0.3.0)
Requires-Dist: orjson (>=2,<4)
Requires-Dist: pydantic (>=2.7,<3.0)
Requires-Dist: pydantic-partial (>=0.5.5,<0.6.0)
Requires-Dist: sse-starlette (>=1.3.0,<2.0.0) ; extra == "server" or extra == "all"
Project-URL: Repository, https://github.com/riyavsinha/langgraph-serve
